driverloader/__init__.py
driverloader/cli.py
driverloader/config.py
driverloader/driver.py
driverloader-0.1.3.dist-info/entry_points.txt
driverloader-0.1.3.dist-info/LICENSE
driverloader-0.1.3.dist-info/WHEEL
driverloader-0.1.3.dist-info/METADATA
driverloader-0.1.3.dist-info/RECORD
