Metadata-Version: 2.1
Name: driverloader
Version: 0.1.3
Summary: A webdriver downloader
Home-page: https://github.com/looker53/webdriver-downloader
License: MIT
Keywords: driverloader,webriver,selenium
Author: yuze
Author-email: looker53@sina.com
Requires-Python: >=3.6,<4.0
Classifier: License :: OSI Approved :: MIT License
Classifier: Programming Language :: Python :: 3
Classifier: Programming Language :: Python :: 3.6
Classifier: Programming Language :: Python :: 3.7
Classifier: Programming Language :: Python :: 3.8
Classifier: Programming Language :: Python :: 3.9
Requires-Dist: click
